supabase_realtime_py/__init__.py
supabase_realtime_py/channel.py
supabase_realtime_py/connection.py
supabase_realtime_py/exceptions.py
supabase_realtime_py/message.py
supabase_realtime_py-0.1.0.dist-info/LICENSE
supabase_realtime_py-0.1.0.dist-info/WHEEL
supabase_realtime_py-0.1.0.dist-info/METADATA
supabase_realtime_py-0.1.0.dist-info/RECORD
