Metadata-Version: 2.1
Name: supabase-realtime-py
Version: 0.1.0
Summary: 
Author: None
Requires-Python: >=3.7,<4.0
Classifier: Programming Language :: Python :: 3
Classifier: Programming Language :: Python :: 3.7
Classifier: Programming Language :: Python :: 3.8
Classifier: Programming Language :: Python :: 3.9
Requires-Dist: dataclasses (>=0.6,<0.7)
Requires-Dist: websockets (>=8.1,<9.0)
